stockpriceanna/__init__.py
stockpriceanna/pricegen.py
stockpriceanna/utils.py
stockpriceanna-1.2.3.dist-info/LICENSE
stockpriceanna-1.2.3.dist-info/METADATA
stockpriceanna-1.2.3.dist-info/WHEEL
stockpriceanna-1.2.3.dist-info/top_level.txt
stockpriceanna-1.2.3.dist-info/RECORD
