Metadata-Version: 2.1
Name: stockpriceanna
Version: 1.2.3
Summary: a collect of tools for analyzing stock prices
Home-page: https://github.com/edwincca/stockpriceanna/blob/master/README.md
Author: DrEdwC
Author-email: edwincca@hotmail.com
License: UNKNOWN
Platform: UNKNOWN
Classifier: Programming Language :: Python :: 3
Classifier: License :: OSI Approved :: MIT License
Classifier: Operating System :: OS Independent
